bulkllm/__init__.py
bulkllm/_version.py
bulkllm/cli.py
bulkllm/llm.py
bulkllm/llm_configs.py
bulkllm/logs.py
bulkllm/rate_limiter.py
bulkllm/rate_limits.py
bulkllm/schema.py
bulkllm/stream_stats.py
bulkllm/task_runner.py
bulkllm/usage_tracker.py
bulkllm/model_registration/__init__.py
bulkllm/model_registration/anthropic.py
bulkllm/model_registration/canonical.py
bulkllm/model_registration/gemini.py
bulkllm/model_registration/main.py
bulkllm/model_registration/mistral.py
bulkllm/model_registration/openai.py
bulkllm/model_registration/openrouter.py
bulkllm/model_registration/utils.py
bulkllm/model_registration/xai.py
bulkllm/model_registration/data/__init__.py
bulkllm/model_registration/data/anthropic.json
bulkllm/model_registration/data/gemini.json
bulkllm/model_registration/data/mistral.json
bulkllm/model_registration/data/openai.json
bulkllm/model_registration/data/openai_detailed.json
bulkllm/model_registration/data/openrouter.json
bulkllm/model_registration/data/xai.json
bulkllm-0.5.12.dist-info/METADATA
bulkllm-0.5.12.dist-info/WHEEL
bulkllm-0.5.12.dist-info/entry_points.txt
bulkllm-0.5.12.dist-info/top_level.txt
bulkllm-0.5.12.dist-info/RECORD
