Metadata-Version: 2.4
Name: bulkllm
Version: 0.5.12
Author: Bryce Drennan
License-Expression: MIT
Project-URL: Documentation, https://github.com/brycedrennan/bulkllm
Project-URL: Source, https://github.com/brycedrennan/bulkllm
Requires-Python: >=3.12
Requires-Dist: anyio>=4.9.0
Requires-Dist: diskcache>=5.6.3
Requires-Dist: litellm>=1.73.0
Requires-Dist: pydantic>=2.11.4
Requires-Dist: python-dotenv>=1.1.0
Requires-Dist: tenacity>=9.1.2
Requires-Dist: typer>=0.15.4
